MANIFEST.in
README.rst
setup.py
docs/HISTORY.txt
docs/INSTALL.txt
docs/LICENSE.GPL
docs/LICENSE.txt
docs/TODO.txt
unice/.DS_Store
unice/__init__.py
unice.portlet.mosaique.egg-info/PKG-INFO
unice.portlet.mosaique.egg-info/SOURCES.txt
unice.portlet.mosaique.egg-info/dependency_links.txt
unice.portlet.mosaique.egg-info/entry_points.txt
unice.portlet.mosaique.egg-info/namespace_packages.txt
unice.portlet.mosaique.egg-info/not-zip-safe
unice.portlet.mosaique.egg-info/requires.txt
unice.portlet.mosaique.egg-info/top_level.txt
unice/portlet/.DS_Store
unice/portlet/__init__.py
unice/portlet/mosaique/.DS_Store
unice/portlet/mosaique/__init__.py
unice/portlet/mosaique/configure.zcml
unice/portlet/mosaique/mosaiqueportlet.pt
unice/portlet/mosaique/mosaiqueportlet.py
unice/portlet/mosaique/vocabularies.py
unice/portlet/mosaique/browser/.DS_Store
unice/portlet/mosaique/browser/__init__.py
unice/portlet/mosaique/browser/configure.zcml
unice/portlet/mosaique/browser/images/.DS_Store
unice/portlet/mosaique/browser/images/controls.psd
unice/portlet/mosaique/browser/javascripts/.DS_Store
unice/portlet/mosaique/browser/javascripts/scripts.js
unice/portlet/mosaique/browser/stylesheets/.DS_Store
unice/portlet/mosaique/browser/stylesheets/styles.css
unice/portlet/mosaique/profiles/.DS_Store
unice/portlet/mosaique/profiles/default/cssregistry.xml
unice/portlet/mosaique/profiles/default/jsregistry.xml
unice/portlet/mosaique/profiles/default/metadata.xml
unice/portlet/mosaique/profiles/default/portlets.xml
unice/portlet/mosaique/tests/__init__.py
unice/portlet/mosaique/tests/base.py
unice/portlet/mosaique/tests/test_portlet.py